magico/__init__.py
magico/__version__.py
magico/json_path_data.py
magico/magico.py
magico-1.0.dist-info/LICENSE
magico-1.0.dist-info/METADATA
magico-1.0.dist-info/WHEEL
magico-1.0.dist-info/top_level.txt
magico-1.0.dist-info/RECORD
