Metadata-Version: 2.1
Name: magico
Version: 1.0
Summary: MagicO - enabling attribute notation and JSONPath
Home-page: https://github.com/jackyko8/magico
Author: Jacky Ko
Author-email: 
License: MIT
Project-URL: Source, https://github.com/jackyko8/magico
Project-URL: Documentation, https://github.com/jackyko8/magico/blob/main/tutorials/MagicO.ipynb
Project-URL: Bug Tracker, https://github.com/jackyko8/magico/issues
Classifier: Programming Language :: Python :: 3
Classifier: License :: OSI Approved :: MIT License
Classifier: Operating System :: OS Independent
Requires-Python: >=3.7
License-File: LICENSE
